ngocbien_analysis/__init__.py
ngocbien_analysis/main.py
ngocbien_analysis/analysis/__init__.py
ngocbien_analysis/utils/__init__.py
ngocbien_analysis/utils/config.py
ngocbien_analysis/utils/utils_.py
ngocbien_analysis/visualization/__init__.py
ngocbien_analysis/visualization/plot.py
ngocbien_analysis-0.3.dist-info/LICENSE.md
ngocbien_analysis-0.3.dist-info/METADATA
ngocbien_analysis-0.3.dist-info/WHEEL
ngocbien_analysis-0.3.dist-info/top_level.txt
ngocbien_analysis-0.3.dist-info/RECORD
